{
	"name": "InvCampaign",
	"properties": {
		"invCampaignId": {
			"type": "number",
			"required": true,
			"length": null,
			"precision": 10,
			"scale": 0,
			"id": 1,
			"mysql": {
				"columnName": "inv_campaign_id",
				"dataType": "int",
				"dataLength": null,
				"dataPrecision": 10,
				"dataScale": 0,
				"nullable": "N"
			},
			"updateOnly": false
		},
		"invCampaignStatus": {
			"type": "string",
			"required": false,
			"length": 20,
			"precision": null,
			"scale": null,
			"mysql": {
				"columnName": "inv_campaign_status",
				"dataType": "varchar",
				"dataLength": 20,
				"dataPrecision": null,
				"dataScale": null,
				"nullable": "Y"
			}
		},
		"invCampaignChk": {
			"type": "number",
			"required": false,
			"length": null,
			"precision": 10,
			"scale": 0,
			"mysql": {
				"columnName": "inv_campaign_chk",
				"dataType": "int",
				"dataLength": null,
				"dataPrecision": 10,
				"dataScale": 0,
				"nullable": "Y"
			}
		},
		"invCampaignName": {
			"type": "string",
			"required": false,
			"length": 100,
			"precision": null,
			"scale": null,
			"mysql": {
				"columnName": "inv_campaign_name",
				"dataType": "varchar",
				"dataLength": 100,
				"dataPrecision": null,
				"dataScale": null,
				"nullable": "Y"
			}
		},
		"invCampaignShortname": {
			"type": "string",
			"required": false,
			"length": 100,
			"precision": null,
			"scale": null,
			"mysql": {
				"columnName": "inv_campaign_shortname",
				"dataType": "varchar",
				"dataLength": 100,
				"dataPrecision": null,
				"dataScale": null,
				"nullable": "Y"
			}
		},
		"invCampaignDescription": {
			"type": "string",
			"required": false,
			"length": 100,
			"precision": null,
			"scale": null,
			"mysql": {
				"columnName": "inv_campaign_description",
				"dataType": "varchar",
				"dataLength": 100,
				"dataPrecision": null,
				"dataScale": null,
				"nullable": "Y"
			}
		},
		"invCampaignQueueId": {
			"type": "string",
			"required": false,
			"length": 20,
			"precision": null,
			"scale": null,
			"mysql": {
				"columnName": "inv_campaign_queue_id",
				"dataType": "varchar",
				"dataLength": 20,
				"dataPrecision": null,
				"dataScale": null,
				"nullable": "Y"
			}
		},
		"invCampaignQueueName": {
			"type": "string",
			"required": false,
			"length": 100,
			"precision": null,
			"scale": null,
			"mysql": {
				"columnName": "inv_campaign_queue_name",
				"dataType": "varchar",
				"dataLength": 100,
				"dataPrecision": null,
				"dataScale": null,
				"nullable": "Y"
			}
		},
		"invCampaignQueueNumber": {
			"type": "string",
			"required": false,
			"length": 20,
			"precision": null,
			"scale": null,
			"mysql": {
				"columnName": "inv_campaign_queue_number",
				"dataType": "varchar",
				"dataLength": 20,
				"dataPrecision": null,
				"dataScale": null,
				"nullable": "Y"
			}
		},
		"invCampaignAftercallTime": {
			"type": "number",
			"required": false,
			"length": null,
			"precision": 10,
			"scale": 0,
			"mysql": {
				"columnName": "inv_campaign_aftercall_time",
				"dataType": "int",
				"dataLength": null,
				"dataPrecision": 10,
				"dataScale": 0,
				"nullable": "Y"
			}
		},
		"invCampaignStart": {
			"type": "string",
			"required": false,
			"length": 100,
			"precision": null,
			"scale": null,
			"mysql": {
				"columnName": "inv_campaign_start",
				"dataType": "varchar",
				"dataLength": 100,
				"dataPrecision": null,
				"dataScale": null,
				"nullable": "Y"
			}
		},
		"invCampaignEnd": {
			"type": "string",
			"required": false,
			"length": 100,
			"precision": null,
			"scale": null,
			"mysql": {
				"columnName": "inv_campaign_end",
				"dataType": "varchar",
				"dataLength": 100,
				"dataPrecision": null,
				"dataScale": null,
				"nullable": "Y"
			}
		},
		"invCampaignStartDateText": {
			"type": "date",
			"required": false,
			"length": null,
			"precision": null,
			"scale": null,
			"mysql": {
				"columnName": "inv_campaign_start_date_text",
				"dataType": "date",
				"dataLength": null,
				"dataPrecision": null,
				"dataScale": null,
				"nullable": "Y"
			}
		},
		"invCampaignEndDateText": {
			"type": "date",
			"required": false,
			"length": null,
			"precision": null,
			"scale": null,
			"mysql": {
				"columnName": "inv_campaign_end_date_text",
				"dataType": "date",
				"dataLength": null,
				"dataPrecision": null,
				"dataScale": null,
				"nullable": "Y"
			}
		},
		"invCampaignStartTimeText": {
			"type": "string",
			"required": false,
			"length": null,
			"precision": null,
			"scale": null,
			"mysql": {
				"columnName": "inv_campaign_start_time_text",
				"dataType": "time",
				"dataLength": null,
				"dataPrecision": null,
				"dataScale": null,
				"nullable": "Y"
			}
		},
		"invCampaignEndTimeText": {
			"type": "string",
			"required": false,
			"length": null,
			"precision": null,
			"scale": null,
			"mysql": {
				"columnName": "inv_campaign_end_time_text",
				"dataType": "time",
				"dataLength": null,
				"dataPrecision": null,
				"dataScale": null,
				"nullable": "Y"
			}
		}
	},
	"settings": {
		"strict": false,
		"forceId": false,
		"replaceOnPUT": true,
		"idInjection": false,
		"mysql": {
			"schema": "system_proser",
			"table": "inv_campaign"
		}
	}
}